turboedit/__init__.py
turboedit/bindings.py
turboedit/lib/libnvec.dll
turboedit/lib/libopenblas.dll
turboedit-0.1.9.dist-info/licenses/LICENSE
turboedit-0.1.9.dist-info/METADATA
turboedit-0.1.9.dist-info/WHEEL
turboedit-0.1.9.dist-info/top_level.txt
turboedit-0.1.9.dist-info/RECORD
