Metadata-Version: 2.4
Name: turboedit
Version: 0.1.9
Summary: Implementation of TurboEdit algorithm for GNSS data
Author-email: Matheus Maica <matheus.maica@unb.ca>
License: MIT License
Project-URL: Homepage, https://github.com/Matheus-Maica
Requires-Python: >=3.7
License-File: LICENSE
Dynamic: license-file
